{
  "module": "pepite7_H_dd_ath",
  "timestamp": "2026-05-11T08:51:02.205628+00:00",
  "version": "1.0.0",
  "mode": "OBSERVATOIRE_READONLY",
  "side_effect_safe": true,
  "execution_allowed": false,
  "exchange_allowed": false,
  "live_allowed": false,
  "validation": {
    "wr_train": 73.68,
    "n_train": 57,
    "wr_test": 76.0,
    "n_test": 25,
    "delta_tt": 2.32,
    "verdict": "TIER_1_PLUS_AUDITE"
  },
  "tire": false,
  "status": "SILENCE",
  "raison": "H>=P90 et dd_ath<=P25 | H=0.1972 P90=0.43497541431166653 dd_ath=0.298540660873364 P25=0.041396699209794",
  "valeurs": {
    "dd_ath": 0.298540660873364,
    "H": 0.1972
  },
  "quantiles": {
    "dd_ath_P25": 0.041396699209794,
    "dd_ath_P75": 0.1883407933127652,
    "dd_ath_P90": 0.2673774404878057,
    "dd_ath_P10": 0.01662087370677428,
    "H_P25": 0.185549246819823,
    "H_P75": 0.3462690547119726,
    "H_P90": 0.43497541431166653,
    "H_P10": 0.12982799337216788
  },
  "sources_valeurs": {
    "dd_ath": "history:dd_ath",
    "H": "today_state"
  },
  "voix": null,
  "label": "SILENCE",
  "sens": "LONG",
  "horizon_jours": 20,
  "sources": {
    "history": "/home/ubuntu/seragone/seragone_v3_final.csv",
    "today": "/home/ubuntu/seragone/state.json",
    "monde": "/home/ubuntu/seragone/multivers_state.json"
  }
}